datalogs/__init__.py
datalogs/_get_filename.py
datalogs/_load_log.py
datalogs/_logger.py
datalogs/_logs.py
datalogs/_variables.py
datalogs/py.typed
datalogs-0.5.1.dist-info/LICENSE
datalogs-0.5.1.dist-info/METADATA
datalogs-0.5.1.dist-info/WHEEL
datalogs-0.5.1.dist-info/RECORD
