Metadata-Version: 2.1
Name: datalogs
Version: 0.5.1
Summary: Python package for logging data from scientific experiments.
Home-page: https://github.com/PainterQubits/datalogs
License: BSD-3-Clause
Author: Alex Hadley
Author-email: contact@alexhadley.net
Requires-Python: >=3.9,<4.0
Classifier: License :: OSI Approved :: BSD License
Classifier: Programming Language :: Python :: 3
Classifier: Programming Language :: Python :: 3.9
Classifier: Programming Language :: Python :: 3.10
Classifier: Programming Language :: Python :: 3.11
Classifier: Programming Language :: Python :: 3.12
Provides-Extra: paramdb
Requires-Dist: netcdf4 (>=1.7.1.post2,<2.0.0)
Requires-Dist: numpy (>=1.26.4,<2.0.0)
Requires-Dist: paramdb (>=0.15.2,<0.16.0) ; extra == "paramdb"
Requires-Dist: typing-extensions (>=4.12.2,<5.0.0)
Requires-Dist: xarray (>=2024.7.0,<2025.0.0)
Project-URL: Repository, https://github.com/PainterQubits/datalogs
